async_limiter/__init__.py
async_limiter/async_limiter.py
async_limiter-1.1.0.dist-info/licenses/LICENSE
async_limiter-1.1.0.dist-info/METADATA
async_limiter-1.1.0.dist-info/WHEEL
async_limiter-1.1.0.dist-info/top_level.txt
async_limiter-1.1.0.dist-info/RECORD
