Metadata-Version: 2.4
Name: async-limiter
Version: 1.1.0
Summary: An asyncio-based rate limiter for API requests
Author-email: Shehryar Sohail <hafizshehryar88@gmail.com>
License-Expression: MIT
Project-URL: Homepage, https://github.com/Shehryar718/async-limiter
Project-URL: Issues, https://github.com/Shehryar718/async-limiter/issues
Classifier: Development Status :: 5 - Production/Stable
Classifier: Intended Audience :: Developers
Classifier: Programming Language :: Python :: 3
Classifier: Programming Language :: Python :: 3.9
Classifier: Programming Language :: Python :: 3.10
Classifier: Programming Language :: Python :: 3.11
Classifier: Topic :: Software Development :: Libraries :: Python Modules
Requires-Python: >=3.9
License-File: LICENSE
Provides-Extra: test
Requires-Dist: pytest>=7.0.0; extra == "test"
Requires-Dist: pytest-asyncio>=0.18.0; extra == "test"
Requires-Dist: aiohttp>=3.8.0; extra == "test"
Dynamic: license-file
